pushikoo_pusher_onebot/__init__.py
pushikoo_pusher_onebot/api.py
pushikoo_pusher_onebot/config.py
pushikoo_pusher_onebot/main.py
pushikoo_pusher_onebot-0.1.2.dist-info/METADATA
pushikoo_pusher_onebot-0.1.2.dist-info/WHEEL
pushikoo_pusher_onebot-0.1.2.dist-info/entry_points.txt
pushikoo_pusher_onebot-0.1.2.dist-info/licenses/LICENSE
pushikoo_pusher_onebot-0.1.2.dist-info/RECORD
