Metadata-Version: 2.4
Name: pushikoo-pusher-onebot
Version: 0.1.2
Summary: OneBot Pusher adapter for Pushikoo.
Project-URL: Homepage, https://github.com/Pushikoo/pushikoo-pusher-onebot
Author: Pushikoo
License-File: LICENSE
Classifier: Operating System :: OS Independent
Classifier: Programming Language :: Python :: 3
Requires-Python: >=3.10
Requires-Dist: loguru
Requires-Dist: pushikoo-interface>=0.3.0
Requires-Dist: requests
Provides-Extra: dev
Requires-Dist: dotenv; extra == 'dev'
Requires-Dist: pytest; extra == 'dev'
Requires-Dist: ruff; extra == 'dev'
